jansbrainfuckkernel/__init__.py
jansbrainfuckkernel/__main__.py
jansbrainfuckkernel/install_kernelspec.py
jansbrainfuckkernel/kernel.py
jansbrainfuckkernel-1.0.1.dist-info/LICENSE
jansbrainfuckkernel-1.0.1.dist-info/METADATA
jansbrainfuckkernel-1.0.1.dist-info/WHEEL
jansbrainfuckkernel-1.0.1.dist-info/entry_points.txt
jansbrainfuckkernel-1.0.1.dist-info/top_level.txt
jansbrainfuckkernel-1.0.1.dist-info/RECORD
